{"2300101":{"name":"Abaiara","holidays":[]},"2300150":{"name":"Acarape","holidays":[]},"2300200":{"name":"Acaraú","holidays":[{"month":1,"day":20,"name":"Feriado Municipal"},{"month":7,"day":31,"name":"Feriado Municipal"},{"month":12,"day":8,"name":"Feriado Municipal"}]},"2300309":{"name":"Acopiara","holidays":[{"month":6,"day":24,"name":"Dia São João"},{"month":9,"day":15,"name":"Feriado Municipal"},{"month":9,"day":28,"name":"Feriado Municipal"},{"month":10,"day":4,"name":"S. Francisco de Assis"}]},"2300408":{"name":"Aiuaba","holidays":[{"month":8,"day":15,"name":"Feriado Municipal"},{"month":9,"day":15,"name":"Feriado Municipal"}]},"2300507":{"name":"Alcântaras","holidays":[]},"2300606":{"name":"Altaneira","holidays":[]},"2300705":{"name":"Alto Santo","holidays":[{"month":6,"day":1,"name":"Feriado Municipal"}]},"2300754":{"name":"Amontada","holidays":[{"month":2,"day":5,"name":"Feriado Municipal"},{"month":7,"day":11,"name":"Feriado Municipal"},{"month":12,"day":8,"name":"Feriado Municipal"}]},"2300804":{"name":"Antonina do Norte","holidays":[]},"2300903":{"name":"Apuiarés","holidays":[]},"2301000":{"name":"Aquiraz","holidays":[{"month":2,"day":13,"name":"Feriado Municipal"},{"month":3,"day":19,"name":"São José"}]},"2301109":{"name":"Aracati","holidays":[{"month":1,"day":20,"name":"São Sebastião"},{"month":3,"day":19,"name":"São José"},{"month":10,"day":7,"name":"Padroeira"},{"month":10,"day":25,"name":"Aniversário"}]},"2301208":{"name":"Aracoiaba","holidays":[{"month":8,"day":16,"name":"Feriado Municipal"},{"month":12,"day":8,"name":"Feriado Municipal"}]},"2301257":{"name":"Ararendá","holidays":[{"month":3,"day":19,"name":"Dia de São José, padroeiro do estado"},{"month":12,"day":21,"name":"Aniversário da cidade"}]},"2301307":{"name":"Araripe","holidays":[{"month":6,"day":13,"name":"Dia de Santo Antônio"},{"month":8,"day":3,"name":"Feriado Municipal"},{"month":11,"day":5,"name":"Feriado Municipal"}]},"2301406":{"name":"Aratuba","holidays":[]},"2301505":{"name":"Arneiroz","holidays":[]},"2301604":{"name":"Assaré","holidays":[{"month":3,"day":5,"name":"Feriado Municipal"},{"month":7,"day":19,"name":"Feriado Municipal"},{"month":9,"day":15,"name":"Feriado Municipal"}]},"2301703":{"name":"Aurora","holidays":[{"month":6,"day":24,"name":"Feriado Municipal"},{"month":11,"day":10,"name":"Dia do Município"}]},"2301802":{"name":"Baixio","holidays":[]},"2301851":{"name":"Banabuiú","holidays":[{"month":1,"day":25,"name":"Feriado Municipal"}]},"2301901":{"name":"Barbalha","holidays":[{"month":6,"day":13,"name":"Dia de Santo Antônio"},{"month":8,"day":17,"name":"Feriado Municipal"},{"month":12,"day":8,"name":"Feriado Municipal"}]},"2301950":{"name":"Barreira","holidays":[{"month":6,"day":29,"name":"Feriado Municipal"}]},"2302008":{"name":"Barro","holidays":[{"month":6,"day":13,"name":"Dia de Santo Antônio"},{"month":11,"day":22,"name":"Feriado Municipal"}]},"2302057":{"name":"Barroquinha","holidays":[]},"2302107":{"name":"Baturité","holidays":[{"month":8,"day":9,"name":"Feriado Municipal"},{"month":8,"day":15,"name":"Feriado Municipal"},{"month":12,"day":8,"name":"Feriado Municipal"},{"month":12,"day":13,"name":"Feriado Municipal"}]},"2302206":{"name":"Beberibe","holidays":[{"month":6,"day":29,"name":"Feriado Municipal"},{"month":7,"day":5,"name":"Feriado Municipal"},{"month":7,"day":16,"name":"Feriado Municipal"}]},"2302305":{"name":"Bela Cruz","holidays":[{"month":2,"day":23,"name":"Feriado Municipal"},{"month":12,"day":8,"name":"Feriado Municipal"}]},"2302404":{"name":"Boa Viagem","holidays":[{"month":10,"day":31,"name":"Feriado Municipal"},{"month":11,"day":21,"name":"Feriado Municipal"}]},"2302503":{"name":"Brejo Santo","holidays":[{"month":6,"day":24,"name":"Feriado Municipal"},{"month":8,"day":26,"name":"Feriado Municipal"},{"month":12,"day":8,"name":"Feriado Municipal"}]},"2302602":{"name":"Camocim","holidays":[{"month":6,"day":29,"name":"Feriado Municipal"},{"month":9,"day":29,"name":"Feriado Municipal"}]},"2302701":{"name":"Campos Sales","holidays":[{"month":7,"day":29,"name":"Feriado Municipal"}]},"2302800":{"name":"Canindé","holidays":[{"month":7,"day":29,"name":"Feriado Municipal"}]},"2302909":{"name":"Capistrano","holidays":[{"month":9,"day":8,"name":"Feriado Municipal"},{"month":11,"day":22,"name":"Feriado Municipal"}]},"2303006":{"name":"Caridade","holidays":[{"month":6,"day":13,"name":"Dia de Santo Antônio"},{"month":8,"day":6,"name":"Feriado Municipal"}]},"2303105":{"name":"Cariré","holidays":[{"month":6,"day":13,"name":"Dia de Santo Antônio"},{"month":9,"day":16,"name":"Feriado Municipal"}]},"2303204":{"name":"Caririaçu","holidays":[{"month":6,"day":29,"name":"Feriado Municipal"},{"month":8,"day":18,"name":"Feriado Municipal"}]},"2303303":{"name":"Cariús","holidays":[]},"2303402":{"name":"Carnaubal","holidays":[{"month":7,"day":22,"name":"Feriado Municipal"},{"month":9,"day":8,"name":"Feriado Municipal"}]},"2303501":{"name":"Cascavel","holidays":[]},"2303600":{"name":"Catarina","holidays":[]},"2303659":{"name":"Catunda","holidays":[]},"2303709":{"name":"Caucaia","holidays":[{"month":3,"day":19,"name":"São José"},{"month":8,"day":15,"name":"Nossa Senhora dos Prazeres"},{"month":10,"day":15,"name":"Dia do Município"}]},"2303808":{"name":"Cedro","holidays":[{"month":3,"day":19,"name":"São José"},{"month":6,"day":24,"name":"Feriado Municipal"}]},"2303907":{"name":"Chaval","holidays":[]},"2303931":{"name":"Choró","holidays":[]},"2303956":{"name":"Chorozinho","holidays":[]},"2304004":{"name":"Coreaú","holidays":[{"month":9,"day":15,"name":"Feriado Municipal"},{"month":9,"day":24,"name":"Feriado Municipal"}]},"2304103":{"name":"Crateús","holidays":[{"month":7,"day":6,"name":"Feriado Municipal"}]},"2304202":{"name":"Crato","holidays":[{"month":3,"day":19,"name":"São José"},{"month":6,"day":21,"name":"Dia do município"},{"month":9,"day":1,"name":"Dia de Nossa Senhora da Penha, padroeira do município"}]},"2304236":{"name":"Croatá","holidays":[{"month":5,"day":3,"name":"Aniversário da Cidade"}]},"2304251":{"name":"Cruz","holidays":[{"month":1,"day":14,"name":"Criação do Município"},{"month":4,"day":6,"name":"Criação da Paróquia"},{"month":10,"day":4,"name":"Dia de São Francisco de Assis, Padroeiro da cidade"},{"month":11,"day":15,"name":"Dia da Macha do Vale"}]},"2304269":{"name":"Deputado Irapuan Pinheiro","holidays":[]},"2304277":{"name":"Ereré","holidays":[]},"2304285":{"name":"Eusébio","holidays":[{"month":6,"day":23,"name":"Feriado Municipal"},{"month":7,"day":26,"name":"Feriado Municipal"}]},"2304301":{"name":"Farias Brito","holidays":[{"month":3,"day":19,"name":"São José"},{"month":12,"day":8,"name":"Feriado Municipal"},{"month":12,"day":20,"name":"Feriado Municipal"}]},"2304350":{"name":"Forquilha","holidays":[]},"2304400":{"name":"Fortaleza","holidays":[{"month":3,"day":19,"name":"São José"},{"month":4,"day":13,"name":"Aniversário de Fortaleza"},{"month":8,"day":15,"name":"Nossa Senhora da Assunção"}]},"2304459":{"name":"Fortim","holidays":[{"month":3,"day":19,"name":"São José"},{"month":3,"day":27,"name":"Feriado Municipal"},{"month":6,"day":29,"name":"Feriado Municipal"},{"month":9,"day":21,"name":"Feriado Municipal"}]},"2304509":{"name":"Frecheirinha","holidays":[{"month":4,"day":1,"name":"Feriado Municipal"},{"month":9,"day":8,"name":"Feriado Municipal"}]},"2304608":{"name":"General Sampaio","holidays":[]},"2304657":{"name":"Graça","holidays":[{"month":4,"day":15,"name":"Feriado Municipal"},{"month":8,"day":15,"name":"Feriado Municipal"}]},"2304707":{"name":"Granja","holidays":[{"month":7,"day":2,"name":"Feriado Municipal"},{"month":11,"day":3,"name":"Feriado Municipal"}]},"2304806":{"name":"Granjeiro","holidays":[]},"2304905":{"name":"Groaíras","holidays":[]},"2304954":{"name":"Guaiúba","holidays":[{"month":9,"day":14,"name":"Feriado Municipal"}]},"2305001":{"name":"Guaraciaba do Norte","holidays":[{"month":5,"day":12,"name":"Feriado Municipal"},{"month":8,"day":15,"name":"Feriado Municipal"}]},"2305100":{"name":"Guaramiranga","holidays":[]},"2305209":{"name":"Hidrolândia","holidays":[{"month":12,"day":8,"name":"Feriado Municipal"},{"month":12,"day":27,"name":"Feriado Municipal"}]},"2305233":{"name":"Horizonte","holidays":[{"month":3,"day":6,"name":"Feriado Municipal"},{"month":3,"day":19,"name":"São José"},{"month":6,"day":24,"name":"Feriado Municipal"}]},"2305266":{"name":"Ibaretama","holidays":[]},"2305308":{"name":"Ibiapina","holidays":[{"month":1,"day":20,"name":"Feriado Municipal"},{"month":3,"day":19,"name":"São José"},{"month":6,"day":29,"name":"Feriado Municipal"},{"month":11,"day":23,"name":"Feriado Municipal"}]},"2305332":{"name":"Ibicuitinga","holidays":[]},"2305357":{"name":"Icapuí","holidays":[{"month":1,"day":22,"name":"Emancipação"},{"month":3,"day":19,"name":"São José"},{"month":9,"day":22,"name":"Feriado Municipal"}]},"2305407":{"name":"Icó","holidays":[{"month":1,"day":2,"name":"Feriado Municipal"},{"month":3,"day":19,"name":"São José"},{"month":12,"day":18,"name":"Feriado Municipal"}]},"2305506":{"name":"Iguatu","holidays":[{"month":1,"day":25,"name":"Aniversário da Cidade"},{"month":3,"day":19,"name":"São José"},{"month":7,"day":26,"name":"Padroeira"}]},"2305605":{"name":"Independência","holidays":[{"month":7,"day":26,"name":"Feriado Municipal"},{"month":12,"day":4,"name":"Feriado Municipal"}]},"2305654":{"name":"Ipaporanga","holidays":[]},"2305704":{"name":"Ipaumirim","holidays":[{"month":1,"day":20,"name":"Feriado Municipal"},{"month":12,"day":8,"name":"Feriado Municipal"},{"month":12,"day":12,"name":"Feriado Municipal"}]},"2305803":{"name":"Ipu","holidays":[{"month":8,"day":26,"name":"Feriado Municipal"}]},"2305902":{"name":"Ipueiras","holidays":[{"month":5,"day":13,"name":"Feriado Municipal"},{"month":12,"day":8,"name":"Feriado Municipal"}]},"2306009":{"name":"Iracema","holidays":[{"month":12,"day":8,"name":"Feriado Municipal"}]},"2306108":{"name":"Irauçuba","holidays":[{"month":5,"day":20,"name":"Feriado Municipal"},{"month":6,"day":21,"name":"Feriado Municipal"}]},"2306207":{"name":"Itaiçaba","holidays":[]},"2306256":{"name":"Itaitinga","holidays":[{"month":3,"day":27,"name":"Feriado Municipal"},{"month":6,"day":13,"name":"Dia de Santo Antônio"}]},"2306306":{"name":"Itapajé","holidays":[{"month":7,"day":20,"name":"Feriado Municipal"}]},"2306405":{"name":"Itapipoca","holidays":[{"month":1,"day":20,"name":"Feriado Municipal"},{"month":8,"day":31,"name":"Feriado Municipal"},{"month":9,"day":24,"name":"Feriado Municipal"}]},"2306504":{"name":"Itapiúna","holidays":[{"month":6,"day":23,"name":"Feriado Municipal"},{"month":12,"day":8,"name":"Feriado Municipal"}]},"2306553":{"name":"Itarema","holidays":[{"month":2,"day":5,"name":"Aniversário"},{"month":6,"day":24,"name":"São João"},{"month":10,"day":13,"name":"N. Sra. de Fátima"}]},"2306603":{"name":"Itatira","holidays":[]},"2306702":{"name":"Jaguaretama","holidays":[{"month":8,"day":29,"name":"Feriado Municipal"},{"month":12,"day":8,"name":"Feriado Municipal"}]},"2306801":{"name":"Jaguaribara","holidays":[{"month":1,"day":10,"name":"Feriado Municipal"},{"month":8,"day":30,"name":"Feriado Municipal"},{"month":9,"day":25,"name":"Feriado Municipal"}]},"2306900":{"name":"Jaguaribe","holidays":[{"month":2,"day":2,"name":"Feriado Municipal"},{"month":11,"day":8,"name":"Feriado Municipal"}]},"2307007":{"name":"Jaguaruana","holidays":[{"month":7,"day":26,"name":"Feriado Municipal"},{"month":9,"day":11,"name":"Feriado Municipal"}]},"2307106":{"name":"Jardim","holidays":[{"month":1,"day":3,"name":"Feriado Municipal"},{"month":6,"day":13,"name":"Dia de Santo Antônio"}]},"2307205":{"name":"Jati","holidays":[]},"2307254":{"name":"Jijoca de Jericoacoara","holidays":[{"month":3,"day":6,"name":"Feriado Municipal"},{"month":12,"day":13,"name":"Feriado Municipal"}]},"2307304":{"name":"Juazeiro do Norte","holidays":[{"month":3,"day":24,"name":"Aniversário Pe. Cícero"},{"month":6,"day":22,"name":"Emancipação Política de Juazeiro"},{"month":7,"day":22,"name":"Emancipação"},{"month":9,"day":15,"name":"Padroeira"}]},"2307403":{"name":"Jucás","holidays":[{"month":7,"day":16,"name":"Feriado Municipal"}]},"2307502":{"name":"Lavras da Mangabeira","holidays":[{"month":8,"day":20,"name":"Feriado Municipal"}]},"2307601":{"name":"Limoeiro do Norte","holidays":[{"month":3,"day":19,"name":"São José"},{"month":8,"day":30,"name":"Feriado Municipal"},{"month":12,"day":8,"name":"Feriado Municipal"}]},"2307635":{"name":"Madalena","holidays":[{"month":8,"day":12,"name":"Feriado Municipal"},{"month":10,"day":31,"name":"Feriado Municipal"}]},"2307650":{"name":"Maracanaú","holidays":[{"month":3,"day":6,"name":"Feriado Municipal"},{"month":3,"day":19,"name":"São José"},{"month":6,"day":13,"name":"Dia de Santo Antônio"}]},"2307700":{"name":"Maranguape","holidays":[{"month":1,"day":20,"name":"Feriado Municipal"},{"month":9,"day":8,"name":"Feriado Municipal"},{"month":11,"day":17,"name":"Feriado Municipal"}]},"2307809":{"name":"Marco","holidays":[]},"2307908":{"name":"Martinópole","holidays":[]},"2308005":{"name":"Massapê","holidays":[]},"2308104":{"name":"Mauriti","holidays":[{"month":8,"day":27,"name":"Feriado Municipal"},{"month":12,"day":8,"name":"Feriado Municipal"}]},"2308203":{"name":"Meruoca","holidays":[{"month":12,"day":8,"name":"Feriado Municipal"}]},"2308302":{"name":"Milagres","holidays":[{"month":8,"day":15,"name":"Feriado Municipal"}]},"2308351":{"name":"Milhã","holidays":[{"month":3,"day":19,"name":"São José"}]},"2308377":{"name":"Miraíma","holidays":[]},"2308401":{"name":"Missão Velha","holidays":[{"month":3,"day":19,"name":"São José"},{"month":7,"day":11,"name":"Feriado Municipal"}]},"2308500":{"name":"Mombaça","holidays":[{"month":8,"day":15,"name":"Feriado Municipal"},{"month":11,"day":27,"name":"Feriado Municipal"},{"month":12,"day":8,"name":"Feriado Municipal"}]},"2308609":{"name":"Monsenhor Tabosa","holidays":[{"month":1,"day":20,"name":"Feriado Municipal"},{"month":11,"day":22,"name":"Feriado Municipal"},{"month":12,"day":13,"name":"Feriado Municipal"}]},"2308708":{"name":"Morada Nova","holidays":[{"month":6,"day":11,"name":"Feriado Municipal"},{"month":8,"day":2,"name":"Feriado Municipal"}]},"2308807":{"name":"Moraújo","holidays":[]},"2308906":{"name":"Morrinhos","holidays":[{"month":9,"day":6,"name":"Feriado Municipal"}]},"2309003":{"name":"Mucambo","holidays":[{"month":12,"day":12,"name":"Feriado Municipal"}]},"2309102":{"name":"Mulungu","holidays":[]},"2309201":{"name":"Nova Olinda","holidays":[]},"2309300":{"name":"Nova Russas","holidays":[{"month":8,"day":15,"name":"Feriado Municipal"},{"month":11,"day":11,"name":"Feriado Municipal"}]},"2309409":{"name":"Novo Oriente","holidays":[]},"2309458":{"name":"Ocara","holidays":[{"month":6,"day":13,"name":"Dia de Santo Antônio"},{"month":11,"day":1,"name":"Feriado Municipal"},{"month":12,"day":28,"name":"Feriado Municipal"}]},"2309508":{"name":"Orós","holidays":[]},"2309607":{"name":"Pacajus","holidays":[{"month":5,"day":23,"name":"Feriado Municipal"},{"month":12,"day":8,"name":"Feriado Municipal"}]},"2309706":{"name":"Pacatuba","holidays":[{"month":7,"day":16,"name":"Feriado Municipal"},{"month":12,"day":8,"name":"Feriado Municipal"}]},"2309805":{"name":"Pacoti","holidays":[{"month":9,"day":2,"name":"Feriado Municipal"},{"month":12,"day":8,"name":"Feriado Municipal"}]},"2309904":{"name":"Pacujá","holidays":[]},"2310001":{"name":"Palhano","holidays":[{"month":5,"day":8,"name":"Feriado Municipal"},{"month":12,"day":8,"name":"Feriado Municipal"}]},"2310100":{"name":"Palmácia","holidays":[{"month":6,"day":23,"name":"Feriado Municipal"},{"month":9,"day":6,"name":"Feriado Municipal"},{"month":11,"day":3,"name":"Feriado Municipal"},{"month":12,"day":8,"name":"Feriado Municipal"}]},"2310209":{"name":"Paracuru","holidays":[{"month":6,"day":29,"name":"Feriado Municipal"},{"month":11,"day":22,"name":"Feriado Municipal"}]},"2310258":{"name":"Paraipaba","holidays":[{"month":11,"day":1,"name":"Feriado Municipal"}]},"2310308":{"name":"Parambu","holidays":[{"month":6,"day":29,"name":"Feriado Municipal"},{"month":9,"day":15,"name":"Feriado Municipal"}]},"2310407":{"name":"Paramoti","holidays":[]},"2310506":{"name":"Pedra Branca","holidays":[]},"2310605":{"name":"Penaforte","holidays":[]},"2310704":{"name":"Pentecoste","holidays":[{"month":8,"day":23,"name":"Feriado Municipal"},{"month":12,"day":8,"name":"Feriado Municipal"}]},"2310803":{"name":"Pereiro","holidays":[{"month":8,"day":30,"name":"Feriado Municipal"},{"month":9,"day":27,"name":"Feriado Municipal"}]},"2310852":{"name":"Pindoretama","holidays":[]},"2310902":{"name":"Piquet Carneiro","holidays":[{"month":7,"day":12,"name":"Feriado Municipal"}]},"2310951":{"name":"Pires Ferreira","holidays":[]},"2311009":{"name":"Poranga","holidays":[]},"2311108":{"name":"Porteiras","holidays":[{"month":12,"day":8,"name":"Feriado Municipal"}]},"2311207":{"name":"Potengi","holidays":[{"month":3,"day":19,"name":"São José"},{"month":4,"day":5,"name":"Feriado Municipal"},{"month":9,"day":4,"name":"Feriado Municipal"}]},"2311231":{"name":"Potiretama","holidays":[]},"2311264":{"name":"Quiterianópolis","holidays":[]},"2311306":{"name":"Quixadá","holidays":[{"month":2,"day":11,"name":"Feriado Municipal"},{"month":3,"day":19,"name":"São José"},{"month":10,"day":27,"name":"Aniversário de Quixadá, Lei 1.960 de 14/12/2000"}]},"2311355":{"name":"Quixelô","holidays":[]},"2311405":{"name":"Quixeramobim","holidays":[{"month":4,"day":15,"name":"Dia do Evangélico"},{"month":6,"day":13,"name":"Dia de Santo Antônio"},{"month":8,"day":14,"name":"Feriado Municipal"}]},"2311504":{"name":"Quixeré","holidays":[{"month":5,"day":15,"name":"Feriado Municipal"},{"month":12,"day":8,"name":"Feriado Municipal"}]},"2311603":{"name":"Redenção","holidays":[{"month":12,"day":8,"name":"Feriado Municipal"},{"month":12,"day":28,"name":"Feriado Municipal"}]},"2311702":{"name":"Reriutaba","holidays":[{"month":8,"day":15,"name":"Feriado Municipal"},{"month":9,"day":25,"name":"Aniversário do Município"}]},"2311801":{"name":"Russas","holidays":[{"month":8,"day":6,"name":"Feriado Municipal"},{"month":11,"day":27,"name":"Feriado Municipal"}]},"2311900":{"name":"Saboeiro","holidays":[{"month":2,"day":2,"name":"Feriado Municipal"},{"month":2,"day":3,"name":"Feriado Municipal"}]},"2311959":{"name":"Salitre","holidays":[{"month":3,"day":19,"name":"São José"}]},"2312007":{"name":"Santana do Acaraú","holidays":[{"month":7,"day":26,"name":"Feriado Municipal"},{"month":11,"day":3,"name":"Feriado Municipal"}]},"2312106":{"name":"Santana do Cariri","holidays":[{"month":7,"day":26,"name":"Feriado Municipal"},{"month":11,"day":25,"name":"Feriado Municipal"}]},"2312205":{"name":"Santa Quitéria","holidays":[{"month":5,"day":22,"name":"Feriado Municipal"},{"month":8,"day":27,"name":"Feriado Municipal"},{"month":10,"day":4,"name":"Homenagem ao Revdo. Monsenhor Luis Ximenes de Aragão Freire. Lei Municipal nº 143."}]},"2312304":{"name":"São Benedito","holidays":[{"month":5,"day":13,"name":"Feriado Municipal"},{"month":11,"day":25,"name":"Feriado Municipal"}]},"2312403":{"name":"São Gonçalo do Amarante","holidays":[{"month":11,"day":27,"name":"Feriado Municipal"}]},"2312502":{"name":"São João do Jaguaribe","holidays":[]},"2312601":{"name":"São Luís do Curu","holidays":[]},"2312700":{"name":"Senador Pompeu","holidays":[{"month":3,"day":19,"name":"São José"},{"month":9,"day":3,"name":"Feriado Municipal"},{"month":9,"day":15,"name":"Feriado Municipal"}]},"2312809":{"name":"Senador Sá","holidays":[]},"2312908":{"name":"Sobral","holidays":[{"month":7,"day":5,"name":"Dia do município"},{"month":12,"day":8,"name":"Padroeira"}]},"2313005":{"name":"Solonópole","holidays":[]},"2313104":{"name":"Tabuleiro do Norte","holidays":[{"month":6,"day":8,"name":"Feriado Municipal"},{"month":8,"day":15,"name":"Feriado Municipal"},{"month":9,"day":8,"name":"Feriado Municipal"}]},"2313203":{"name":"Tamboril","holidays":[{"month":1,"day":22,"name":"Feriado Municipal"}]},"2313252":{"name":"Tarrafas","holidays":[]},"2313302":{"name":"Tauá","holidays":[{"month":5,"day":3,"name":"Feriado Municipal"}]},"2313351":{"name":"Tejuçuoca","holidays":[{"month":1,"day":13,"name":"Feriado Municipal"},{"month":6,"day":29,"name":"Feriado Municipal"}]},"2313401":{"name":"Tianguá","holidays":[{"month":7,"day":26,"name":"Feriado Municipal"},{"month":7,"day":31,"name":"Feriado Municipal"}]},"2313500":{"name":"Trairi","holidays":[{"month":11,"day":22,"name":"Feriado Municipal"}]},"2313559":{"name":"Tururu","holidays":[{"month":8,"day":2,"name":"Feriado Municipal"},{"month":12,"day":8,"name":"Feriado Municipal"}]},"2313609":{"name":"Ubajara","holidays":[{"month":8,"day":24,"name":"Feriado Municipal"},{"month":12,"day":31,"name":"Feriado Municipal"}]},"2313708":{"name":"Umari","holidays":[]},"2313757":{"name":"Umirim","holidays":[{"month":2,"day":5,"name":"Feriado Municipal"},{"month":9,"day":8,"name":"Feriado Municipal"},{"month":12,"day":8,"name":"Feriado Municipal"}]},"2313807":{"name":"Uruburetama","holidays":[{"month":3,"day":19,"name":"São José"},{"month":6,"day":24,"name":"Feriado Municipal"},{"month":8,"day":1,"name":"Feriado Municipal"},{"month":11,"day":1,"name":"Feriado Municipal"}]},"2313906":{"name":"Uruoca","holidays":[{"month":3,"day":26,"name":"Feriado Municipal"},{"month":8,"day":15,"name":"Feriado Municipal"}]},"2313955":{"name":"Varjota","holidays":[{"month":2,"day":5,"name":"Feriado Municipal"},{"month":7,"day":26,"name":"Feriado Municipal"}]},"2314003":{"name":"Várzea Alegre","holidays":[{"month":8,"day":31,"name":"Feriado Municipal"}]},"2314102":{"name":"Viçosa do Ceará","holidays":[{"month":8,"day":14,"name":"Feriado Municipal"},{"month":8,"day":15,"name":"Feriado Municipal"}]}}